{
  "latestIso": "2026-07-05",
  "startByWindow": {
    "30d": "2026-06-06",
    "6m": "2026-01-04",
    "1y": "2025-07-06"
  },
  "note": "cell = per-digit accuracy / all-correct rate",
  "tables": {
    "fourOpen": "| Market | 30d | 6m | 1y |\n|---|---:|---:|---:|\n| Sridevi | 72.5% / 20.0% | 73.6% / 24.3% | 73.3% / 23.5% |\n| Time Bazar | 73.0% / 24.0% | 71.9% / 20.8% | 72.1% / 20.9% |\n| Madhur Day | 78.3% / 26.7% | 74.3% / 24.9% | 74.1% / 23.6% |\n| Milan Day | 72.4% / 21.1% | 73.3% / 19.6% | 74.3% / 22.7% |\n| Rajdhani Day | 68.0% / 16.0% | 71.3% / 22.1% | 72.4% / 22.8% |\n| Kalyan | 78.0% / 20.0% | 72.9% / 22.1% | 71.8% / 19.5% |\n| Sridevi Night | 76.7% / 23.3% | 74.4% / 22.1% | 74.2% / 23.8% |\n| Kalyan Night | 64.7% / 11.8% | 71.6% / 20.0% | 71.6% / 18.2% |\n| Madhur Night | 74.0% / 24.0% | 76.0% / 29.9% | 74.6% / 26.2% |\n| Milan Night | 74.0% / 28.0% | 71.2% / 22.9% | 72.3% / 20.8% |\n| Rajdhani Night | 67.5% / 5.0% | 73.4% / 23.4% | 73.5% / 22.2% |\n| Main Bazar | 78.8% / 30.0% | 73.6% / 23.6% | 72.2% / 18.7% |",
    "fourClose": "| Market | 30d | 6m | 1y |\n|---|---:|---:|---:|\n| Sridevi | 75.0% / 26.7% | 73.3% / 19.9% | 72.9% / 19.3% |\n| Time Bazar | 73.0% / 28.0% | 71.6% / 20.8% | 71.0% / 19.3% |\n| Madhur Day | 74.2% / 26.7% | 72.5% / 22.1% | 72.4% / 20.7% |\n| Milan Day | 69.7% / 15.8% | 73.0% / 23.0% | 72.1% / 21.0% |\n| Rajdhani Day | 73.0% / 16.0% | 70.1% / 13.6% | 71.5% / 16.9% |\n| Kalyan | 74.0% / 28.0% | 72.2% / 18.8% | 72.0% / 19.2% |\n| Sridevi Night | 75.0% / 33.3% | 71.4% / 20.4% | 70.6% / 18.2% |\n| Kalyan Night | 72.1% / 23.5% | 73.2% / 23.2% | 73.1% / 22.7% |\n| Madhur Night | 73.0% / 28.0% | 73.1% / 23.4% | 71.9% / 18.9% |\n| Milan Night | 66.0% / 12.0% | 70.4% / 17.0% | 71.0% / 18.5% |\n| Rajdhani Night | 72.5% / 15.0% | 73.6% / 21.9% | 73.4% / 22.6% |\n| Main Bazar | 73.8% / 15.0% | 73.8% / 23.6% | 73.3% / 23.1% |",
    "threeOpen": "| Market | 30d | 6m | 1y |\n|---|---:|---:|---:|\n| Sridevi | 75.6% / 43.3% | 74.0% / 39.8% | 73.4% / 37.0% |\n| Time Bazar | 74.7% / 36.0% | 71.0% / 29.9% | 71.9% / 33.9% |\n| Madhur Day | 77.8% / 40.0% | 74.4% / 37.6% | 74.1% / 35.8% |\n| Milan Day | 70.2% / 21.1% | 73.9% / 34.5% | 75.8% / 38.6% |\n| Rajdhani Day | 64.0% / 20.0% | 71.4% / 33.8% | 72.1% / 32.8% |\n| Kalyan | 76.0% / 32.0% | 73.6% / 33.8% | 72.0% / 31.5% |\n| Sridevi Night | 77.8% / 40.0% | 75.0% / 39.8% | 74.3% / 37.6% |\n| Kalyan Night | 66.7% / 35.3% | 71.5% / 35.2% | 71.0% / 32.0% |\n| Madhur Night | 70.7% / 24.0% | 74.2% / 39.0% | 73.6% / 37.4% |\n| Milan Night | 77.3% / 40.0% | 70.8% / 31.4% | 71.4% / 31.2% |\n| Rajdhani Night | 73.3% / 30.0% | 73.7% / 37.5% | 74.5% / 37.3% |\n| Main Bazar | 80.0% / 45.0% | 73.5% / 39.4% | 72.4% / 34.7% |",
    "threeClose": "| Market | 30d | 6m | 1y |\n|---|---:|---:|---:|\n| Sridevi | 74.4% / 30.0% | 72.7% / 30.4% | 72.9% / 31.5% |\n| Time Bazar | 72.0% / 44.0% | 71.2% / 33.1% | 72.5% / 34.9% |\n| Madhur Day | 77.8% / 43.3% | 74.8% / 38.7% | 73.5% / 35.2% |\n| Milan Day | 73.7% / 42.1% | 74.3% / 37.8% | 73.9% / 37.3% |\n| Rajdhani Day | 76.0% / 48.0% | 72.9% / 33.1% | 72.7% / 32.8% |\n| Kalyan | 73.3% / 32.0% | 73.4% / 35.7% | 72.4% / 32.1% |\n| Sridevi Night | 80.0% / 46.7% | 72.0% / 32.6% | 70.5% / 29.8% |\n| Kalyan Night | 78.4% / 47.1% | 72.5% / 34.4% | 72.9% / 34.8% |\n| Madhur Night | 68.0% / 32.0% | 72.9% / 37.0% | 72.5% / 34.8% |\n| Milan Night | 68.0% / 32.0% | 71.5% / 30.1% | 71.8% / 31.5% |\n| Rajdhani Night | 70.0% / 25.0% | 73.2% / 35.2% | 72.8% / 35.3% |\n| Main Bazar | 73.3% / 30.0% | 73.2% / 35.4% | 72.0% / 34.3% |"
  },
  "raw": {
    "3": [
      {
        "market": "Sridevi",
        "open": {
          "30d": {
            "n": 30,
            "perDigit": 0.7555555555555555,
            "allCorrect": 0.43333333333333335,
            "avgCorrect": 2.2666666666666666
          },
          "6m": {
            "n": 181,
            "perDigit": 0.7403314917127072,
            "allCorrect": 0.39779005524861877,
            "avgCorrect": 2.2209944751381214
          },
          "1y": {
            "n": 362,
            "perDigit": 0.7338858195211786,
            "allCorrect": 0.3701657458563536,
            "avgCorrect": 2.201657458563536
          }
        },
        "close": {
          "30d": {
            "n": 30,
            "perDigit": 0.7444444444444445,
            "allCorrect": 0.3,
            "avgCorrect": 2.2333333333333334
          },
          "6m": {
            "n": 181,
            "perDigit": 0.7274401473296501,
            "allCorrect": 0.30386740331491713,
            "avgCorrect": 2.18232044198895
          },
          "1y": {
            "n": 362,
            "perDigit": 0.7292817679558011,
            "allCorrect": 0.3149171270718232,
            "avgCorrect": 2.1878453038674035
          }
        }
      },
      {
        "market": "Time Bazar",
        "open": {
          "30d": {
            "n": 25,
            "perDigit": 0.7466666666666667,
            "allCorrect": 0.36,
            "avgCorrect": 2.24
          },
          "6m": {
            "n": 154,
            "perDigit": 0.70995670995671,
            "allCorrect": 0.2987012987012987,
            "avgCorrect": 2.1298701298701297
          },
          "1y": {
            "n": 301,
            "perDigit": 0.7187153931339978,
            "allCorrect": 0.3388704318936877,
            "avgCorrect": 2.1561461794019934
          }
        },
        "close": {
          "30d": {
            "n": 25,
            "perDigit": 0.72,
            "allCorrect": 0.44,
            "avgCorrect": 2.16
          },
          "6m": {
            "n": 154,
            "perDigit": 0.7121212121212122,
            "allCorrect": 0.33116883116883117,
            "avgCorrect": 2.1363636363636362
          },
          "1y": {
            "n": 301,
            "perDigit": 0.7253599114064231,
            "allCorrect": 0.3488372093023256,
            "avgCorrect": 2.176079734219269
          }
        }
      },
      {
        "market": "Madhur Day",
        "open": {
          "30d": {
            "n": 30,
            "perDigit": 0.7777777777777778,
            "allCorrect": 0.4,
            "avgCorrect": 2.3333333333333335
          },
          "6m": {
            "n": 181,
            "perDigit": 0.7440147329650092,
            "allCorrect": 0.3756906077348066,
            "avgCorrect": 2.2320441988950277
          },
          "1y": {
            "n": 352,
            "perDigit": 0.7414772727272727,
            "allCorrect": 0.35795454545454547,
            "avgCorrect": 2.2244318181818183
          }
        },
        "close": {
          "30d": {
            "n": 30,
            "perDigit": 0.7777777777777778,
            "allCorrect": 0.43333333333333335,
            "avgCorrect": 2.3333333333333335
          },
          "6m": {
            "n": 181,
            "perDigit": 0.7476979742173112,
            "allCorrect": 0.3867403314917127,
            "avgCorrect": 2.2430939226519335
          },
          "1y": {
            "n": 352,
            "perDigit": 0.7348484848484849,
            "allCorrect": 0.3522727272727273,
            "avgCorrect": 2.2045454545454546
          }
        }
      },
      {
        "market": "Milan Day",
        "open": {
          "30d": {
            "n": 19,
            "perDigit": 0.7017543859649122,
            "allCorrect": 0.21052631578947367,
            "avgCorrect": 2.1052631578947367
          },
          "6m": {
            "n": 148,
            "perDigit": 0.7387387387387387,
            "allCorrect": 0.34459459459459457,
            "avgCorrect": 2.2162162162162162
          },
          "1y": {
            "n": 295,
            "perDigit": 0.7581920903954802,
            "allCorrect": 0.3864406779661017,
            "avgCorrect": 2.2745762711864406
          }
        },
        "close": {
          "30d": {
            "n": 19,
            "perDigit": 0.7368421052631579,
            "allCorrect": 0.42105263157894735,
            "avgCorrect": 2.210526315789474
          },
          "6m": {
            "n": 148,
            "perDigit": 0.7432432432432432,
            "allCorrect": 0.3783783783783784,
            "avgCorrect": 2.22972972972973
          },
          "1y": {
            "n": 295,
            "perDigit": 0.7389830508474576,
            "allCorrect": 0.3728813559322034,
            "avgCorrect": 2.216949152542373
          }
        }
      },
      {
        "market": "Rajdhani Day",
        "open": {
          "30d": {
            "n": 25,
            "perDigit": 0.64,
            "allCorrect": 0.2,
            "avgCorrect": 1.92
          },
          "6m": {
            "n": 154,
            "perDigit": 0.7142857142857143,
            "allCorrect": 0.33766233766233766,
            "avgCorrect": 2.142857142857143
          },
          "1y": {
            "n": 302,
            "perDigit": 0.7207505518763797,
            "allCorrect": 0.32781456953642385,
            "avgCorrect": 2.162251655629139
          }
        },
        "close": {
          "30d": {
            "n": 25,
            "perDigit": 0.76,
            "allCorrect": 0.48,
            "avgCorrect": 2.28
          },
          "6m": {
            "n": 154,
            "perDigit": 0.7294372294372294,
            "allCorrect": 0.33116883116883117,
            "avgCorrect": 2.188311688311688
          },
          "1y": {
            "n": 302,
            "perDigit": 0.7273730684326711,
            "allCorrect": 0.32781456953642385,
            "avgCorrect": 2.1821192052980134
          }
        }
      },
      {
        "market": "Kalyan",
        "open": {
          "30d": {
            "n": 25,
            "perDigit": 0.76,
            "allCorrect": 0.32,
            "avgCorrect": 2.28
          },
          "6m": {
            "n": 154,
            "perDigit": 0.7359307359307359,
            "allCorrect": 0.33766233766233766,
            "avgCorrect": 2.207792207792208
          },
          "1y": {
            "n": 302,
            "perDigit": 0.7196467991169978,
            "allCorrect": 0.31456953642384106,
            "avgCorrect": 2.1589403973509933
          }
        },
        "close": {
          "30d": {
            "n": 25,
            "perDigit": 0.7333333333333333,
            "allCorrect": 0.32,
            "avgCorrect": 2.2
          },
          "6m": {
            "n": 154,
            "perDigit": 0.7337662337662337,
            "allCorrect": 0.35714285714285715,
            "avgCorrect": 2.2012987012987013
          },
          "1y": {
            "n": 302,
            "perDigit": 0.7240618101545254,
            "allCorrect": 0.3211920529801324,
            "avgCorrect": 2.172185430463576
          }
        }
      },
      {
        "market": "Sridevi Night",
        "open": {
          "30d": {
            "n": 30,
            "perDigit": 0.7777777777777778,
            "allCorrect": 0.4,
            "avgCorrect": 2.3333333333333335
          },
          "6m": {
            "n": 181,
            "perDigit": 0.7495395948434622,
            "allCorrect": 0.39779005524861877,
            "avgCorrect": 2.248618784530387
          },
          "1y": {
            "n": 362,
            "perDigit": 0.7430939226519337,
            "allCorrect": 0.3756906077348066,
            "avgCorrect": 2.229281767955801
          }
        },
        "close": {
          "30d": {
            "n": 30,
            "perDigit": 0.8,
            "allCorrect": 0.4666666666666667,
            "avgCorrect": 2.4
          },
          "6m": {
            "n": 181,
            "perDigit": 0.7200736648250461,
            "allCorrect": 0.3259668508287293,
            "avgCorrect": 2.160220994475138
          },
          "1y": {
            "n": 362,
            "perDigit": 0.7053406998158379,
            "allCorrect": 0.2983425414364641,
            "avgCorrect": 2.116022099447514
          }
        }
      },
      {
        "market": "Kalyan Night",
        "open": {
          "30d": {
            "n": 17,
            "perDigit": 0.6666666666666666,
            "allCorrect": 0.35294117647058826,
            "avgCorrect": 2
          },
          "6m": {
            "n": 125,
            "perDigit": 0.7146666666666667,
            "allCorrect": 0.352,
            "avgCorrect": 2.144
          },
          "1y": {
            "n": 247,
            "perDigit": 0.7098515519568152,
            "allCorrect": 0.31983805668016196,
            "avgCorrect": 2.1295546558704452
          }
        },
        "close": {
          "30d": {
            "n": 17,
            "perDigit": 0.7843137254901961,
            "allCorrect": 0.47058823529411764,
            "avgCorrect": 2.3529411764705883
          },
          "6m": {
            "n": 125,
            "perDigit": 0.7253333333333334,
            "allCorrect": 0.344,
            "avgCorrect": 2.176
          },
          "1y": {
            "n": 247,
            "perDigit": 0.728744939271255,
            "allCorrect": 0.3481781376518219,
            "avgCorrect": 2.1862348178137654
          }
        }
      },
      {
        "market": "Madhur Night",
        "open": {
          "30d": {
            "n": 25,
            "perDigit": 0.7066666666666667,
            "allCorrect": 0.24,
            "avgCorrect": 2.12
          },
          "6m": {
            "n": 154,
            "perDigit": 0.7424242424242424,
            "allCorrect": 0.38961038961038963,
            "avgCorrect": 2.227272727272727
          },
          "1y": {
            "n": 302,
            "perDigit": 0.7362030905077263,
            "allCorrect": 0.3741721854304636,
            "avgCorrect": 2.2086092715231787
          }
        },
        "close": {
          "30d": {
            "n": 25,
            "perDigit": 0.68,
            "allCorrect": 0.32,
            "avgCorrect": 2.04
          },
          "6m": {
            "n": 154,
            "perDigit": 0.7294372294372294,
            "allCorrect": 0.37012987012987014,
            "avgCorrect": 2.188311688311688
          },
          "1y": {
            "n": 302,
            "perDigit": 0.7251655629139073,
            "allCorrect": 0.347682119205298,
            "avgCorrect": 2.1754966887417218
          }
        }
      },
      {
        "market": "Milan Night",
        "open": {
          "30d": {
            "n": 25,
            "perDigit": 0.7733333333333333,
            "allCorrect": 0.4,
            "avgCorrect": 2.32
          },
          "6m": {
            "n": 153,
            "perDigit": 0.7080610021786492,
            "allCorrect": 0.3137254901960784,
            "avgCorrect": 2.1241830065359477
          },
          "1y": {
            "n": 298,
            "perDigit": 0.7136465324384788,
            "allCorrect": 0.31208053691275167,
            "avgCorrect": 2.140939597315436
          }
        },
        "close": {
          "30d": {
            "n": 25,
            "perDigit": 0.68,
            "allCorrect": 0.32,
            "avgCorrect": 2.04
          },
          "6m": {
            "n": 153,
            "perDigit": 0.7145969498910676,
            "allCorrect": 0.3006535947712418,
            "avgCorrect": 2.1437908496732025
          },
          "1y": {
            "n": 298,
            "perDigit": 0.7181208053691275,
            "allCorrect": 0.31543624161073824,
            "avgCorrect": 2.1543624161073827
          }
        }
      },
      {
        "market": "Rajdhani Night",
        "open": {
          "30d": {
            "n": 20,
            "perDigit": 0.7333333333333333,
            "allCorrect": 0.3,
            "avgCorrect": 2.2
          },
          "6m": {
            "n": 128,
            "perDigit": 0.7369791666666666,
            "allCorrect": 0.375,
            "avgCorrect": 2.2109375
          },
          "1y": {
            "n": 252,
            "perDigit": 0.7447089947089947,
            "allCorrect": 0.373015873015873,
            "avgCorrect": 2.234126984126984
          }
        },
        "close": {
          "30d": {
            "n": 20,
            "perDigit": 0.7,
            "allCorrect": 0.25,
            "avgCorrect": 2.1
          },
          "6m": {
            "n": 128,
            "perDigit": 0.7317708333333334,
            "allCorrect": 0.3515625,
            "avgCorrect": 2.1953125
          },
          "1y": {
            "n": 252,
            "perDigit": 0.7275132275132276,
            "allCorrect": 0.3531746031746032,
            "avgCorrect": 2.1825396825396823
          }
        }
      },
      {
        "market": "Main Bazar",
        "open": {
          "30d": {
            "n": 20,
            "perDigit": 0.8,
            "allCorrect": 0.45,
            "avgCorrect": 2.4
          },
          "6m": {
            "n": 127,
            "perDigit": 0.7349081364829396,
            "allCorrect": 0.3937007874015748,
            "avgCorrect": 2.204724409448819
          },
          "1y": {
            "n": 251,
            "perDigit": 0.7237715803452855,
            "allCorrect": 0.3466135458167331,
            "avgCorrect": 2.1713147410358564
          }
        },
        "close": {
          "30d": {
            "n": 20,
            "perDigit": 0.7333333333333333,
            "allCorrect": 0.3,
            "avgCorrect": 2.2
          },
          "6m": {
            "n": 127,
            "perDigit": 0.7322834645669292,
            "allCorrect": 0.3543307086614173,
            "avgCorrect": 2.1968503937007875
          },
          "1y": {
            "n": 251,
            "perDigit": 0.7197875166002656,
            "allCorrect": 0.3426294820717131,
            "avgCorrect": 2.1593625498007967
          }
        }
      }
    ],
    "4": [
      {
        "market": "Sridevi",
        "open": {
          "30d": {
            "n": 30,
            "perDigit": 0.725,
            "allCorrect": 0.2,
            "avgCorrect": 2.9
          },
          "6m": {
            "n": 181,
            "perDigit": 0.7361878453038674,
            "allCorrect": 0.2430939226519337,
            "avgCorrect": 2.9447513812154695
          },
          "1y": {
            "n": 362,
            "perDigit": 0.7334254143646409,
            "allCorrect": 0.23480662983425415,
            "avgCorrect": 2.9337016574585637
          }
        },
        "close": {
          "30d": {
            "n": 30,
            "perDigit": 0.75,
            "allCorrect": 0.26666666666666666,
            "avgCorrect": 3
          },
          "6m": {
            "n": 181,
            "perDigit": 0.7334254143646409,
            "allCorrect": 0.19889502762430938,
            "avgCorrect": 2.9337016574585637
          },
          "1y": {
            "n": 362,
            "perDigit": 0.7285911602209945,
            "allCorrect": 0.19337016574585636,
            "avgCorrect": 2.914364640883978
          }
        }
      },
      {
        "market": "Time Bazar",
        "open": {
          "30d": {
            "n": 25,
            "perDigit": 0.73,
            "allCorrect": 0.24,
            "avgCorrect": 2.92
          },
          "6m": {
            "n": 154,
            "perDigit": 0.7191558441558441,
            "allCorrect": 0.2077922077922078,
            "avgCorrect": 2.8766233766233764
          },
          "1y": {
            "n": 301,
            "perDigit": 0.7209302325581395,
            "allCorrect": 0.20930232558139536,
            "avgCorrect": 2.883720930232558
          }
        },
        "close": {
          "30d": {
            "n": 25,
            "perDigit": 0.73,
            "allCorrect": 0.28,
            "avgCorrect": 2.92
          },
          "6m": {
            "n": 154,
            "perDigit": 0.7159090909090909,
            "allCorrect": 0.2077922077922078,
            "avgCorrect": 2.8636363636363638
          },
          "1y": {
            "n": 301,
            "perDigit": 0.7101328903654485,
            "allCorrect": 0.19269102990033224,
            "avgCorrect": 2.840531561461794
          }
        }
      },
      {
        "market": "Madhur Day",
        "open": {
          "30d": {
            "n": 30,
            "perDigit": 0.7833333333333333,
            "allCorrect": 0.26666666666666666,
            "avgCorrect": 3.1333333333333333
          },
          "6m": {
            "n": 181,
            "perDigit": 0.7430939226519337,
            "allCorrect": 0.24861878453038674,
            "avgCorrect": 2.972375690607735
          },
          "1y": {
            "n": 352,
            "perDigit": 0.7414772727272727,
            "allCorrect": 0.23579545454545456,
            "avgCorrect": 2.965909090909091
          }
        },
        "close": {
          "30d": {
            "n": 30,
            "perDigit": 0.7416666666666667,
            "allCorrect": 0.26666666666666666,
            "avgCorrect": 2.966666666666667
          },
          "6m": {
            "n": 181,
            "perDigit": 0.7251381215469613,
            "allCorrect": 0.22099447513812154,
            "avgCorrect": 2.9005524861878453
          },
          "1y": {
            "n": 352,
            "perDigit": 0.7244318181818182,
            "allCorrect": 0.20738636363636365,
            "avgCorrect": 2.897727272727273
          }
        }
      },
      {
        "market": "Milan Day",
        "open": {
          "30d": {
            "n": 19,
            "perDigit": 0.7236842105263158,
            "allCorrect": 0.21052631578947367,
            "avgCorrect": 2.8947368421052633
          },
          "6m": {
            "n": 148,
            "perDigit": 0.7331081081081081,
            "allCorrect": 0.19594594594594594,
            "avgCorrect": 2.9324324324324325
          },
          "1y": {
            "n": 295,
            "perDigit": 0.7432203389830508,
            "allCorrect": 0.2271186440677966,
            "avgCorrect": 2.9728813559322034
          }
        },
        "close": {
          "30d": {
            "n": 19,
            "perDigit": 0.6973684210526315,
            "allCorrect": 0.15789473684210525,
            "avgCorrect": 2.789473684210526
          },
          "6m": {
            "n": 148,
            "perDigit": 0.7297297297297297,
            "allCorrect": 0.22972972972972974,
            "avgCorrect": 2.918918918918919
          },
          "1y": {
            "n": 295,
            "perDigit": 0.7211864406779661,
            "allCorrect": 0.21016949152542372,
            "avgCorrect": 2.8847457627118644
          }
        }
      },
      {
        "market": "Rajdhani Day",
        "open": {
          "30d": {
            "n": 25,
            "perDigit": 0.68,
            "allCorrect": 0.16,
            "avgCorrect": 2.72
          },
          "6m": {
            "n": 154,
            "perDigit": 0.7126623376623377,
            "allCorrect": 0.22077922077922077,
            "avgCorrect": 2.8506493506493507
          },
          "1y": {
            "n": 302,
            "perDigit": 0.7235099337748344,
            "allCorrect": 0.22847682119205298,
            "avgCorrect": 2.8940397350993377
          }
        },
        "close": {
          "30d": {
            "n": 25,
            "perDigit": 0.73,
            "allCorrect": 0.16,
            "avgCorrect": 2.92
          },
          "6m": {
            "n": 154,
            "perDigit": 0.7012987012987013,
            "allCorrect": 0.13636363636363635,
            "avgCorrect": 2.8051948051948052
          },
          "1y": {
            "n": 302,
            "perDigit": 0.7152317880794702,
            "allCorrect": 0.16887417218543047,
            "avgCorrect": 2.8609271523178808
          }
        }
      },
      {
        "market": "Kalyan",
        "open": {
          "30d": {
            "n": 25,
            "perDigit": 0.78,
            "allCorrect": 0.2,
            "avgCorrect": 3.12
          },
          "6m": {
            "n": 154,
            "perDigit": 0.7288961038961039,
            "allCorrect": 0.22077922077922077,
            "avgCorrect": 2.9155844155844157
          },
          "1y": {
            "n": 302,
            "perDigit": 0.7177152317880795,
            "allCorrect": 0.19536423841059603,
            "avgCorrect": 2.870860927152318
          }
        },
        "close": {
          "30d": {
            "n": 25,
            "perDigit": 0.74,
            "allCorrect": 0.28,
            "avgCorrect": 2.96
          },
          "6m": {
            "n": 154,
            "perDigit": 0.7224025974025974,
            "allCorrect": 0.18831168831168832,
            "avgCorrect": 2.8896103896103895
          },
          "1y": {
            "n": 302,
            "perDigit": 0.7201986754966887,
            "allCorrect": 0.19205298013245034,
            "avgCorrect": 2.880794701986755
          }
        }
      },
      {
        "market": "Sridevi Night",
        "open": {
          "30d": {
            "n": 30,
            "perDigit": 0.7666666666666667,
            "allCorrect": 0.23333333333333334,
            "avgCorrect": 3.066666666666667
          },
          "6m": {
            "n": 181,
            "perDigit": 0.744475138121547,
            "allCorrect": 0.22099447513812154,
            "avgCorrect": 2.977900552486188
          },
          "1y": {
            "n": 362,
            "perDigit": 0.7417127071823204,
            "allCorrect": 0.23756906077348067,
            "avgCorrect": 2.9668508287292816
          }
        },
        "close": {
          "30d": {
            "n": 30,
            "perDigit": 0.75,
            "allCorrect": 0.3333333333333333,
            "avgCorrect": 3
          },
          "6m": {
            "n": 181,
            "perDigit": 0.7140883977900553,
            "allCorrect": 0.20441988950276244,
            "avgCorrect": 2.856353591160221
          },
          "1y": {
            "n": 362,
            "perDigit": 0.7058011049723757,
            "allCorrect": 0.18232044198895028,
            "avgCorrect": 2.8232044198895028
          }
        }
      },
      {
        "market": "Kalyan Night",
        "open": {
          "30d": {
            "n": 17,
            "perDigit": 0.6470588235294118,
            "allCorrect": 0.11764705882352941,
            "avgCorrect": 2.588235294117647
          },
          "6m": {
            "n": 125,
            "perDigit": 0.716,
            "allCorrect": 0.2,
            "avgCorrect": 2.864
          },
          "1y": {
            "n": 247,
            "perDigit": 0.7155870445344129,
            "allCorrect": 0.18218623481781376,
            "avgCorrect": 2.8623481781376516
          }
        },
        "close": {
          "30d": {
            "n": 17,
            "perDigit": 0.7205882352941176,
            "allCorrect": 0.23529411764705882,
            "avgCorrect": 2.8823529411764706
          },
          "6m": {
            "n": 125,
            "perDigit": 0.732,
            "allCorrect": 0.232,
            "avgCorrect": 2.928
          },
          "1y": {
            "n": 247,
            "perDigit": 0.7307692307692307,
            "allCorrect": 0.22672064777327935,
            "avgCorrect": 2.923076923076923
          }
        }
      },
      {
        "market": "Madhur Night",
        "open": {
          "30d": {
            "n": 25,
            "perDigit": 0.74,
            "allCorrect": 0.24,
            "avgCorrect": 2.96
          },
          "6m": {
            "n": 154,
            "perDigit": 0.7597402597402597,
            "allCorrect": 0.2987012987012987,
            "avgCorrect": 3.038961038961039
          },
          "1y": {
            "n": 302,
            "perDigit": 0.7458609271523179,
            "allCorrect": 0.26158940397350994,
            "avgCorrect": 2.9834437086092715
          }
        },
        "close": {
          "30d": {
            "n": 25,
            "perDigit": 0.73,
            "allCorrect": 0.28,
            "avgCorrect": 2.92
          },
          "6m": {
            "n": 154,
            "perDigit": 0.7305194805194806,
            "allCorrect": 0.23376623376623376,
            "avgCorrect": 2.9220779220779223
          },
          "1y": {
            "n": 302,
            "perDigit": 0.7193708609271523,
            "allCorrect": 0.18874172185430463,
            "avgCorrect": 2.877483443708609
          }
        }
      },
      {
        "market": "Milan Night",
        "open": {
          "30d": {
            "n": 25,
            "perDigit": 0.74,
            "allCorrect": 0.28,
            "avgCorrect": 2.96
          },
          "6m": {
            "n": 153,
            "perDigit": 0.7124183006535948,
            "allCorrect": 0.22875816993464052,
            "avgCorrect": 2.849673202614379
          },
          "1y": {
            "n": 298,
            "perDigit": 0.7231543624161074,
            "allCorrect": 0.2080536912751678,
            "avgCorrect": 2.8926174496644297
          }
        },
        "close": {
          "30d": {
            "n": 25,
            "perDigit": 0.66,
            "allCorrect": 0.12,
            "avgCorrect": 2.64
          },
          "6m": {
            "n": 153,
            "perDigit": 0.704248366013072,
            "allCorrect": 0.16993464052287582,
            "avgCorrect": 2.816993464052288
          },
          "1y": {
            "n": 298,
            "perDigit": 0.709731543624161,
            "allCorrect": 0.18456375838926176,
            "avgCorrect": 2.838926174496644
          }
        }
      },
      {
        "market": "Rajdhani Night",
        "open": {
          "30d": {
            "n": 20,
            "perDigit": 0.675,
            "allCorrect": 0.05,
            "avgCorrect": 2.7
          },
          "6m": {
            "n": 128,
            "perDigit": 0.734375,
            "allCorrect": 0.234375,
            "avgCorrect": 2.9375
          },
          "1y": {
            "n": 252,
            "perDigit": 0.7351190476190477,
            "allCorrect": 0.2222222222222222,
            "avgCorrect": 2.9404761904761907
          }
        },
        "close": {
          "30d": {
            "n": 20,
            "perDigit": 0.725,
            "allCorrect": 0.15,
            "avgCorrect": 2.9
          },
          "6m": {
            "n": 128,
            "perDigit": 0.736328125,
            "allCorrect": 0.21875,
            "avgCorrect": 2.9453125
          },
          "1y": {
            "n": 252,
            "perDigit": 0.7341269841269841,
            "allCorrect": 0.2261904761904762,
            "avgCorrect": 2.9365079365079363
          }
        }
      },
      {
        "market": "Main Bazar",
        "open": {
          "30d": {
            "n": 20,
            "perDigit": 0.7875,
            "allCorrect": 0.3,
            "avgCorrect": 3.15
          },
          "6m": {
            "n": 127,
            "perDigit": 0.7362204724409449,
            "allCorrect": 0.23622047244094488,
            "avgCorrect": 2.9448818897637796
          },
          "1y": {
            "n": 251,
            "perDigit": 0.7221115537848606,
            "allCorrect": 0.18725099601593626,
            "avgCorrect": 2.8884462151394423
          }
        },
        "close": {
          "30d": {
            "n": 20,
            "perDigit": 0.7375,
            "allCorrect": 0.15,
            "avgCorrect": 2.95
          },
          "6m": {
            "n": 127,
            "perDigit": 0.7381889763779528,
            "allCorrect": 0.23622047244094488,
            "avgCorrect": 2.952755905511811
          },
          "1y": {
            "n": 251,
            "perDigit": 0.7330677290836654,
            "allCorrect": 0.23107569721115537,
            "avgCorrect": 2.9322709163346614
          }
        }
      }
    ]
  }
}